odoo/addons/edi_party_data_oca/README.rst
odoo/addons/edi_party_data_oca/__init__.py
odoo/addons/edi_party_data_oca/__manifest__.py
odoo/addons/edi_party_data_oca/utils.py
odoo/addons/edi_party_data_oca/components/__init__.py
odoo/addons/edi_party_data_oca/components/common.py
odoo/addons/edi_party_data_oca/components/party_data.py
odoo/addons/edi_party_data_oca/i18n/edi_party_data_oca.pot
odoo/addons/edi_party_data_oca/i18n/it.po
odoo/addons/edi_party_data_oca/models/__init__.py
odoo/addons/edi_party_data_oca/models/edi_exchange_type.py
odoo/addons/edi_party_data_oca/readme/CONFIGURE.md
odoo/addons/edi_party_data_oca/readme/CONTRIBUTORS.md
odoo/addons/edi_party_data_oca/readme/DESCRIPTION.md
odoo/addons/edi_party_data_oca/readme/USAGE.md
odoo/addons/edi_party_data_oca/static/description/icon.png
odoo/addons/edi_party_data_oca/static/description/index.html
odoo/addons/edi_party_data_oca/tests/__init__.py
odoo/addons/edi_party_data_oca/tests/test_party_data.py
odoo/addons/edi_party_data_oca/views/edi_exchange_type_views.xml
odoo_addon_edi_party_data_oca-18.0.1.0.1.dist-info/METADATA
odoo_addon_edi_party_data_oca-18.0.1.0.1.dist-info/WHEEL
odoo_addon_edi_party_data_oca-18.0.1.0.1.dist-info/top_level.txt
odoo_addon_edi_party_data_oca-18.0.1.0.1.dist-info/RECORD
