Metadata-Version: 2.1
Name: odoo-addon-edi_party_data_oca
Version: 18.0.1.0.1
Requires-Python: >=3.10
Requires-Dist: odoo-addon-edi_component_oca==18.0.*
Requires-Dist: odoo-addon-partner_identification==18.0.*
Requires-Dist: odoo==18.0.*
Summary: Allow to configure and retrieve party information for EDI exchanges.
Home-page: https://github.com/OCA/edi-framework
License: AGPL-3
Author: Camptocamp, Odoo Community Association (OCA)
Author-email: support@odoo-community.org
Classifier: Programming Language :: Python
Classifier: Framework :: Odoo
Classifier: Framework :: Odoo :: 18.0
Classifier: License :: OSI Approved :: GNU Affero General Public License v3
Classifier: Development Status :: 3 - Alpha
